odoo/addons/pingen/README.rst
odoo/addons/pingen/__init__.py
odoo/addons/pingen/__manifest__.py
odoo/addons/pingen/controllers/__init__.py
odoo/addons/pingen/controllers/main.py
odoo/addons/pingen/data/pingen_data.xml
odoo/addons/pingen/i18n/es.po
odoo/addons/pingen/i18n/fr.po
odoo/addons/pingen/i18n/it.po
odoo/addons/pingen/i18n/pingen.pot
odoo/addons/pingen/models/__init__.py
odoo/addons/pingen/models/base_config_settings.py
odoo/addons/pingen/models/ir_attachment.py
odoo/addons/pingen/models/pingen.py
odoo/addons/pingen/models/pingen_document.py
odoo/addons/pingen/models/res_company.py
odoo/addons/pingen/readme/CONFIGURE.rst
odoo/addons/pingen/readme/CONTRIBUTORS.rst
odoo/addons/pingen/readme/DESCRIPTION.rst
odoo/addons/pingen/readme/USAGE.rst
odoo/addons/pingen/security/ir.model.access.csv
odoo/addons/pingen/static/description/icon.png
odoo/addons/pingen/static/description/index.html
odoo/addons/pingen/tests/__init__.py
odoo/addons/pingen/tests/test_pingen.py
odoo/addons/pingen/tests/fixtures/cassettes/test_pingen_push_document.yaml
odoo/addons/pingen/views/base_config_settings.xml
odoo/addons/pingen/views/ir_attachment_view.xml
odoo/addons/pingen/views/pingen_document_view.xml
odoo_addon_pingen-16.0.1.1.0.2.dist-info/METADATA
odoo_addon_pingen-16.0.1.1.0.2.dist-info/WHEEL
odoo_addon_pingen-16.0.1.1.0.2.dist-info/top_level.txt
odoo_addon_pingen-16.0.1.1.0.2.dist-info/RECORD
