Metadata-Version: 2.1
Name: odoo-addon-pingen
Version: 16.0.1.1.0.2
Summary: pingen.com integration
Home-page: https://github.com/OCA/report-print-send
Author: Camptocamp,Odoo Community Association (OCA)
Author-email: support@odoo-community.org
License: AGPL-3
Classifier: Programming Language :: Python
Classifier: Framework :: Odoo
Classifier: Framework :: Odoo :: 16.0
Classifier: License :: OSI Approved :: GNU Affero General Public License v3
Requires-Python: >=3.10
Requires-Dist: oauthlib
Requires-Dist: odoo<16.1dev,>=16.0a
Requires-Dist: requests-oauthlib
